{
  "1": [
    { "eventId": "evt-vs-dust-veil-536", "matchText": "536 Dust Veil" },
    { "eventId": "evt-vs-536-sun-dimming", "matchText": "sun gave little heat or light" },
    { "eventId": "evt-vs-540-second-eruption", "matchText": "second major volcanic event around 540" },
    { "eventId": "evt-vs-gold-hoards-536", "matchText": "Late Roman Gold Hoards" },
    { "eventId": "evt-vs-fimbulwinter-echo", "matchText": "Fimbulwinter" },
    { "eventId": "evt-vs-bracteates", "matchText": "bracteates" },
    { "eventId": "evt-vs-sosdala-style", "matchText": "animal style" },
    { "eventId": "evt-vs-depopulation-recovery", "matchText": "Scandinavia Begins to Recover" }
  ],
  "2": [
    { "eventId": "evt-vs-vendel-graves", "matchText": "Vendel Boat-Graves" },
    { "eventId": "evt-vs-valsgarde", "matchText": "Valsgärde" },
    { "eventId": "evt-vs-vendel-helmets", "matchText": "Vendel helmets" },
    { "eventId": "evt-vs-sutton-hoo-link", "matchText": "Sutton Hoo" },
    { "eventId": "evt-vs-ring-swords", "matchText": "ring-swords" },
    { "eventId": "evt-vs-warrior-retinue", "matchText": "Warrior Retinue and the Mead-Hall" },
    { "eventId": "evt-vs-uppland-aristocracy", "matchText": "Uppland Warrior Aristocracy" },
    { "eventId": "evt-vs-foil-garnet-work", "matchText": "Gold-and-Garnet Cloisonne Craft" },
    { "eventId": "evt-vs-boat-burial-ritual", "matchText": "Boat-Grave Ritual" }
  ],
  "3": [
    { "eventId": "evt-vs-old-uppsala", "matchText": "Royal Mounds of Old Uppsala" },
    { "eventId": "evt-vs-ynglings", "matchText": "Yngling Dynasty" },
    { "eventId": "evt-vs-three-great-mounds", "matchText": "Three Great Uppsala Barrows" },
    { "eventId": "evt-vs-ynglingatal", "matchText": "Ynglingatal" },
    { "eventId": "evt-vs-sacral-kingship", "matchText": "sacral kingship" },
    { "eventId": "evt-vs-beowulf", "matchText": "World of Beowulf" },
    { "eventId": "evt-vs-geats-swedes", "matchText": "Geats and the Swedes" },
    { "eventId": "evt-vs-hrolf-kraki", "matchText": "Hrolf Kraki" },
    { "eventId": "evt-vs-danish-kingdoms-legendary", "matchText": "Lejre" }
  ],
  "4": [
    { "eventId": "evt-vs-norse-religion", "matchText": "Norse Pagan Religion Takes Shape" },
    { "eventId": "evt-vs-odin-war-god", "matchText": "Odin as the God of Warriors and Kings" },
    { "eventId": "evt-vs-thor-freyr", "matchText": "Thor and Freyr" },
    { "eventId": "evt-vs-blot-sacrifice", "matchText": "blot" },
    { "eventId": "evt-vs-votive-deposits", "matchText": "Weapon Deposits in Bogs and Lakes" },
    { "eventId": "evt-vs-gotland-stones", "matchText": "Gotland picture stones" },
    { "eventId": "evt-vs-picture-stone-valhalla", "matchText": "Picture Stones and Valhalla Imagery" },
    { "eventId": "evt-vs-ship-symbolism", "matchText": "Ship as Religious Symbol" },
    { "eventId": "evt-vs-uppsala-temple", "matchText": "Sacrifices at Uppsala" },
    { "eventId": "evt-vs-sacred-grove", "matchText": "Sacred Grove and the Outdoor Cult" }
  ],
  "5": [
    { "eventId": "evt-vs-helgo", "matchText": "Trading Site of Helgo" },
    { "eventId": "evt-vs-helgo-buddha", "matchText": "Helgo Buddha" },
    { "eventId": "evt-vs-helgo-coptic", "matchText": "Coptic Ladle and Irish Crozier" },
    { "eventId": "evt-vs-helgo-workshops", "matchText": "Helgo as a Production Center" },
    { "eventId": "evt-vs-malaren-network", "matchText": "Malaren Basin Trade Network" },
    { "eventId": "evt-vs-grobina", "matchText": "Grobina" },
    { "eventId": "evt-vs-frisian-trade", "matchText": "Frisian Trade Link" },
    { "eventId": "evt-vs-amber-trade", "matchText": "Amber and Bead Trade" },
    { "eventId": "evt-vs-fur-trade", "matchText": "Arctic Fur Economy" },
    { "eventId": "evt-vs-baltic-networks", "matchText": "Baltic Trade World" }
  ],
  "6": [
    { "eventId": "evt-vs-ribe", "matchText": "Trading Town of Ribe" },
    { "eventId": "evt-vs-ribe-planned-plots", "matchText": "Ribe's Planned Market Plots" },
    { "eventId": "evt-vs-sceattas", "matchText": "Sceattas Minted at Ribe" },
    { "eventId": "evt-vs-wodan-monster-coin", "matchText": "Wodan-Monster Coinage" },
    { "eventId": "evt-vs-silver-economy", "matchText": "Silver Enters the Scandinavian Economy" },
    { "eventId": "evt-vs-craft-specialization", "matchText": "Craft Specialization at the Emporia" },
    { "eventId": "evt-vs-glass-bead-production", "matchText": "Glass Bead Production and Trade" },
    { "eventId": "evt-vs-thrall-economy", "matchText": "Slavery and the Thrall Economy" },
    { "eventId": "evt-vs-dorestad", "matchText": "Dorestad and the Frankish Connection" },
    { "eventId": "evt-vs-ahus-emporium", "matchText": "Ahus as an Early Emporium" }
  ],
  "7": [
    { "eventId": "evt-vs-clinker", "matchText": "Clinker-Built Construction Perfected" },
    { "eventId": "evt-vs-the-sail", "matchText": "Sail Reaches Scandinavia" },
    { "eventId": "evt-vs-hull-evolution", "matchText": "From River Boat to Ocean Ship" },
    { "eventId": "evt-vs-younger-futhark", "matchText": "Younger Futhark" },
    { "eventId": "evt-vs-elder-futhark", "matchText": "Elder Futhark" },
    { "eventId": "evt-vs-runestones", "matchText": "Runestone Tradition Develops" },
    { "eventId": "evt-vs-danish-border-fortification", "matchText": "Danevirke" },
    { "eventId": "evt-vs-petty-kingdoms-norway", "matchText": "Petty Kingdoms of Norway" },
    { "eventId": "evt-vs-salme", "matchText": "Salme Ship Burials" },
    { "eventId": "evt-vs-salme-ship-two", "matchText": "Salme II Ship" },
    { "eventId": "evt-vs-salme-dna", "matchText": "DNA Evidence at Salme" },
    { "eventId": "evt-vs-frankish-pressure", "matchText": "Frankish Expansion and the Danish Border" }
  ],
  "8": [
    { "eventId": "evt-vs-restless-aristocracy", "matchText": "Restless Younger Sons" },
    { "eventId": "evt-vs-surplus-production", "matchText": "Agricultural Surplus and Population Growth" },
    { "eventId": "evt-vs-ottar", "matchText": "Ohthere's Northern World" },
    { "eventId": "evt-vs-ohthere-navigation", "matchText": "Navigating the Northern Waters" },
    { "eventId": "evt-vs-coastal-monasteries-vulnerable", "matchText": "Vulnerable Wealth on the Western Coasts" },
    { "eventId": "evt-vs-portland-incident", "matchText": "Portland incident" },
    { "eventId": "evt-vs-eve-of-vikings", "matchText": "Eve of the Viking Age" },
    { "eventId": "evt-vs-lindisfarne-launch", "matchText": "Longships Sail for Lindisfarne" },
    { "eventId": "evt-vs-inter-scandinavian-wars", "matchText": "Inter-Scandinavian Conflicts" }
  ]
}
